{"Collections":[{"sheetName":"Sheet1","startColumn":"A","endColumn":"A","startRow":"2","endRow":"+","comment":"","rule":"Individual: @D*\nTypes: Procedure","active":true},{"sheetName":"Sheet1","startColumn":"A","endColumn":"A","startRow":"2","endRow":"+","comment":"","rule":"Individual: @C*\nTypes: ObservableProperty\nFacts: isObservedBy @B*","active":true},{"sheetName":"Sheet1","startColumn":"A","endColumn":"A","startRow":"2","endRow":"+","comment":"","rule":"Individual: @E*\nTypes: FeatureOfInterest","active":true},{"sheetName":"Sheet1","startColumn":"A","endColumn":"A","startRow":"2","endRow":"+","comment":"","rule":"Individual: @A*\nTypes: Platform","active":true},{"sheetName":"Sheet1","startColumn":"A","endColumn":"A","startRow":"2","endRow":"+","comment":"","rule":"Individual: @B*\nTypes: Sensor\nFacts: isHostedBy @A*,\n\tusedProcedure @D*","active":true}]}